LICENSE.txt
README.rst
pyicontract_lint_meta.py
setup.py
icontract_lint/__init__.py
icontract_lint/main.py
pyicontract_lint.egg-info/PKG-INFO
pyicontract_lint.egg-info/SOURCES.txt
pyicontract_lint.egg-info/dependency_links.txt
pyicontract_lint.egg-info/entry_points.txt
pyicontract_lint.egg-info/requires.txt
pyicontract_lint.egg-info/top_level.txt