Metadata-Version: 2.1
Name: pyicontract-lint
Version: 2.1.3
Summary: Lint contracts defined with icontract library.
Home-page: https://github.com/Parquery/pyicontract-lint
Author: Marko Ristin
Author-email: marko.ristin@gmail.com
License: License :: OSI Approved :: MIT License
Keywords: design-by-contract precondition postcondition validation lint
Platform: UNKNOWN
Classifier: Development Status :: 5 - Production/Stable
Classifier: Intended Audience :: Developers
Classifier: License :: OSI Approved :: MIT License
Classifier: Programming Language :: Python :: 3.6
Classifier: Programming Language :: Python :: 3.7
Classifier: Programming Language :: Python :: 3.8
Classifier: Operating System :: Microsoft :: Windows
Classifier: Operating System :: POSIX
Provides-Extra: dev
